{
  "name": "Malaric",
  "title": "The Shadow's Whisper",
  "titlees": "El Susurro de las Sombras",
  "description": "Malaric, the Shadow's Whisper, is the inscrutable god of secrets, forbidden lore, and the destruction of foes. This mortal-turned-deity is a master of deception, his true intentions an enigma. His followers, often lurking in secret societies, seek hidden truths to gain power. Malaric wears many masks, bearing names like 'The Unseeing Eye' and 'The Unmaker'. Those who honor him know that knowledge is power, and power shapes fate.",
  "descriptiones": "Malaric, el Susurro de la Sombra, es el inescrutable dios de los secretos, la sabiduría prohibida y la destrucción de los enemigos. Este mortal convertido en deidad es un maestro del engaño y sus verdaderas intenciones son un enigma. Sus seguidores, en sociedades secretas, buscan verdades ocultas para obtener poder. Malaric lleva muchas máscaras, con nombres como «El Ojo que no Ve» y «El Deshacedor». Quienes le rinden honor saben que el conocimiento es poder y que el poder determina el destino.",
  "thumbnail": "malaric.jpg",
  "god": true,
  "social": [
    {
      "name": "Instagram",
      "url": "https://www.instagram.com/drusniel/"
    },
    {
      "name": "Twitter",
      "url": "https://twitter.com/twitter"
    },
    {
      "name": "Website",
      "url": "https://danielsobrado.com"
    }
  ],
  "skills": [
    "Skin Walker",
    "Assassin"
  ],
  "skillses": [
    "Metaforsis",
    "Asesino"
  ]
}
